{
  "version": 1,
  "last_audit": {
    "path": ".prism/second-pass/audit-2026-04-28T23-00-50.json",
    "generated_at": "2026-04-28T23:00:50.026Z",
    "scope": "HEAD~5..HEAD",
    "counts": {
      "error": 0,
      "warning": 0,
      "info": 0,
      "confirmed": 0,
      "probable": 0,
      "candidate": 0
    }
  },
  "recent_files": [],
  "layout": {
    "sidebar_width": 218,
    "problems_width": 360,
    "preview_height": 465,
    "agent_pane_width": 448,
    "preview_visible": true,
    "terminal_visible": false,
    "agent_visible": true
  }
}